{
  "updatedAt": "2026-07-08T02:11:18.015Z",
  "jobs": [
    {
      "id": "jumpit-54393989",
      "source": "jumpit",
      "title": "이미지 프로세싱 알고리즘 개발 신입",
      "company": "포스로직",
      "location": "경기 안양시 동안구",
      "experience": "경력 무관",
      "stack": [
        "C",
        "C++",
        "DeepLearning",
        "MachineLearning",
        "AI/인공지능",
        "CUDA"
      ],
      "url": "https://www.jumpit.co.kr/position/54393989",
      "postedAt": "2026-07-08T02:09:31.963Z",
      "deadline": "2026-08-06",
      "score": 90,
      "reason": "DS/ML 핵심 직무 · 스택 6개 일치 · 경력 신입/무관",
      "flags": []
    },
    {
      "id": "jumpit-54363106",
      "source": "jumpit",
      "title": "AI 서비스 백엔드 개발자(경력)",
      "company": "네비웍스",
      "location": "경기",
      "experience": "경력 무관",
      "stack": [
        "Linux",
        "Python",
        "PyTorch",
        "TensorFlow",
        "DeepLearning",
        "AI/인공지능"
      ],
      "url": "https://www.jumpit.co.kr/position/54363106",
      "postedAt": "2026-07-08T02:09:44.930Z",
      "deadline": "2026-08-06",
      "score": 90,
      "reason": "DS/ML 핵심 직무 · 스택 5개 일치 · 경력 신입/무관",
      "flags": []
    },
    {
      "id": "jumpit-54392311",
      "source": "jumpit",
      "title": "AI 엔지니어 채용",
      "company": "레플리",
      "location": "서울 강남구",
      "experience": "경력 무관",
      "stack": [
        "Amazon Kinesis Firehose",
        "AWS Lambda",
        "Docker",
        "Elasticsearch",
        "Python",
        "Redis",
        "AWS",
        "FastAPI"
      ],
      "url": "https://www.jumpit.co.kr/position/54392311",
      "postedAt": "2026-07-08T02:09:31.963Z",
      "deadline": "2026-08-06",
      "score": 83,
      "reason": "DS/ML 핵심 직무 · 스택 2개 일치 · 경력 신입/무관",
      "flags": []
    },
    {
      "id": "jumpit-54360464",
      "source": "jumpit",
      "title": "백엔드 개발자",
      "company": "패스트레인",
      "location": "서울 강남구",
      "experience": "경력 무관",
      "stack": [
        "Docker",
        "Java",
        "Kafka",
        "Kubernetes",
        "MySQL",
        "Spring",
        "Hibernate",
        "REST API"
      ],
      "url": "https://www.jumpit.co.kr/position/54360464",
      "postedAt": "2026-07-08T02:09:31.963Z",
      "deadline": "2026-08-06",
      "score": 63,
      "reason": "백엔드/SW 개발 · 스택 2개 일치 · 경력 신입/무관",
      "flags": []
    },
    {
      "id": "jumpit-54396634",
      "source": "jumpit",
      "title": "Robot Controls Engineer",
      "company": "셀틱스테크놀로지",
      "location": "경기 용인시 처인구",
      "experience": "경력 무관",
      "stack": [
        "C#",
        "C++",
        "Python",
        "Embedded",
        "RTOS"
      ],
      "url": "https://www.jumpit.co.kr/position/54396634",
      "postedAt": "2026-07-08T02:09:31.963Z",
      "deadline": "2026-08-06",
      "score": 55,
      "reason": "직무 미매칭 · 스택 6개 일치 · 경력 신입/무관",
      "flags": []
    },
    {
      "id": "jumpit-54360488",
      "source": "jumpit",
      "title": "프론트엔드 개발자",
      "company": "패스트레인",
      "location": "서울 강남구",
      "experience": "경력 무관",
      "stack": [
        "Confluence",
        "GitHub",
        "Jira",
        "Python",
        "React"
      ],
      "url": "https://www.jumpit.co.kr/position/54360488",
      "postedAt": "2026-07-08T02:09:31.963Z",
      "deadline": "2026-08-06",
      "score": 48,
      "reason": "직무 미매칭 · 스택 2개 일치 · 경력 신입/무관",
      "flags": []
    },
    {
      "id": "jumpit-54378994",
      "source": "jumpit",
      "title": "펌웨어/플랫폼 개발(경력10~15년)",
      "company": "아세아텍",
      "location": "대구 달성군",
      "experience": "경력 무관",
      "stack": [
        "C",
        "HW",
        "FW"
      ],
      "url": "https://www.jumpit.co.kr/position/54378994",
      "postedAt": "2026-07-08T02:09:31.963Z",
      "deadline": "2026-08-06",
      "score": 45,
      "reason": "직무 미매칭 · 스택 4개 일치 · 경력 신입/무관",
      "flags": []
    },
    {
      "id": "jumpit-54379008",
      "source": "jumpit",
      "title": "펌웨어/플랫폼 개발(경력16~20년)",
      "company": "아세아텍",
      "location": "대구 달성군",
      "experience": "경력 무관",
      "stack": [
        "C",
        "HW",
        "FW"
      ],
      "url": "https://www.jumpit.co.kr/position/54379008",
      "postedAt": "2026-07-08T02:09:31.963Z",
      "deadline": "2026-08-06",
      "score": 45,
      "reason": "직무 미매칭 · 스택 4개 일치 · 경력 신입/무관",
      "flags": []
    },
    {
      "id": "jumpit-54378837",
      "source": "jumpit",
      "title": "펌웨어/플랫폼 개발(경력3~9년)",
      "company": "아세아텍",
      "location": "대구 달성군",
      "experience": "경력 무관",
      "stack": [
        "C",
        "HW",
        "FW"
      ],
      "url": "https://www.jumpit.co.kr/position/54378837",
      "postedAt": "2026-07-08T02:09:31.963Z",
      "deadline": "2026-08-06",
      "score": 45,
      "reason": "직무 미매칭 · 스택 4개 일치 · 경력 신입/무관",
      "flags": []
    },
    {
      "id": "jumpit-54377716",
      "source": "jumpit",
      "title": "S/W 소프트웨어 개발 - 신입",
      "company": "씨앤지 마이크로웨이브",
      "location": "대전 유성구",
      "experience": "경력 무관",
      "stack": [
        "C#",
        "WPF",
        "SW",
        "Vb.net"
      ],
      "url": "https://www.jumpit.co.kr/position/54377716",
      "postedAt": "2026-07-08T02:09:31.963Z",
      "deadline": "2026-08-06",
      "score": 45,
      "reason": "직무 미매칭 · 스택 4개 일치 · 경력 신입/무관",
      "flags": []
    },
    {
      "id": "jumpit-54377744",
      "source": "jumpit",
      "title": "S/W 소프트웨어 개발 - 경력",
      "company": "씨앤지 마이크로웨이브",
      "location": "대전 유성구",
      "experience": "경력 무관",
      "stack": [
        "C#",
        "WPF",
        "SW",
        "Vb.net"
      ],
      "url": "https://www.jumpit.co.kr/position/54377744",
      "postedAt": "2026-07-08T02:09:31.963Z",
      "deadline": "2026-08-06",
      "score": 45,
      "reason": "직무 미매칭 · 스택 4개 일치 · 경력 신입/무관",
      "flags": []
    },
    {
      "id": "jumpit-54404363",
      "source": "jumpit",
      "title": "산업용 청소로봇 솔루션 엔지니어",
      "company": "대원씨티에스",
      "location": "서울 영등포구",
      "experience": "경력 무관",
      "stack": [
        "Kubernetes",
        "AI/인공지능"
      ],
      "url": "https://www.jumpit.co.kr/position/54404363",
      "postedAt": "2026-07-08T02:09:31.963Z",
      "deadline": "2026-08-06",
      "score": 40,
      "reason": "직무 미매칭 · 스택 1개 일치 · 경력 신입/무관",
      "flags": []
    },
    {
      "id": "jumpit-54350334",
      "source": "jumpit",
      "title": "전송망 관제 및 운영 신입 채용",
      "company": "드림디엔엠",
      "location": "서울 송파구",
      "experience": "경력 무관",
      "stack": [
        "Router",
        "Network"
      ],
      "url": "https://www.jumpit.co.kr/position/54350334",
      "postedAt": "2026-07-08T02:09:44.930Z",
      "deadline": "2026-08-01",
      "score": 40,
      "reason": "직무 미매칭 · 스택 1개 일치 · 경력 신입/무관",
      "flags": []
    },
    {
      "id": "jumpit-54397427",
      "source": "jumpit",
      "title": "그룹사 SAP 시스템 운영(HR모듈)",
      "company": "한국네트웍스",
      "location": "경기",
      "experience": "경력 무관",
      "stack": [
        "ABAP",
        "SAP"
      ],
      "url": "https://www.jumpit.co.kr/position/54397427",
      "postedAt": "2026-07-08T02:09:31.963Z",
      "deadline": "2026-08-06",
      "score": 32,
      "reason": "직무 미매칭 · 스택 정보 부족 · 경력 신입/무관",
      "flags": []
    },
    {
      "id": "jumpit-54380848",
      "source": "jumpit",
      "title": "하드웨어(H/W)&펌웨어(F/W) 개발자",
      "company": "에스디바이오센서",
      "location": "경기 수원시",
      "experience": "경력 무관",
      "stack": [
        "HW",
        "MCU"
      ],
      "url": "https://www.jumpit.co.kr/position/54380848",
      "postedAt": "2026-07-08T02:09:31.963Z",
      "deadline": "2026-08-06",
      "score": 32,
      "reason": "직무 미매칭 · 스택 정보 부족 · 경력 신입/무관",
      "flags": []
    },
    {
      "id": "jumpit-54363151",
      "source": "jumpit",
      "title": "Software Quality Assurance",
      "company": "네비웍스",
      "location": "경기",
      "experience": "경력 무관",
      "stack": [
        "GitHub",
        "QA",
        "HW",
        "SW"
      ],
      "url": "https://www.jumpit.co.kr/position/54363151",
      "postedAt": "2026-07-08T02:09:31.963Z",
      "deadline": "2026-08-06",
      "score": 32,
      "reason": "직무 미매칭 · 스택 정보 부족 · 경력 신입/무관",
      "flags": []
    },
    {
      "id": "jumpit-54377767",
      "source": "jumpit",
      "title": "S/W 소프트웨어 설계(신입)",
      "company": "씨앤지 마이크로웨이브",
      "location": "대전",
      "experience": "경력 무관",
      "stack": [
        "Linux",
        "SW",
        "MCU",
        "ARM"
      ],
      "url": "https://www.jumpit.co.kr/position/54377767",
      "postedAt": "2026-07-08T02:09:31.963Z",
      "deadline": "2026-08-06",
      "score": 30,
      "reason": "직무 미매칭 · 스택 1개 일치 · 경력 신입/무관",
      "flags": []
    },
    {
      "id": "jumpit-54377793",
      "source": "jumpit",
      "title": "S/W 소프트웨어 설계(경력)",
      "company": "씨앤지 마이크로웨이브",
      "location": "대전",
      "experience": "경력 무관",
      "stack": [
        "Linux",
        "SW",
        "MCU",
        "ARM"
      ],
      "url": "https://www.jumpit.co.kr/position/54377793",
      "postedAt": "2026-07-08T02:09:31.963Z",
      "deadline": "2026-08-06",
      "score": 30,
      "reason": "직무 미매칭 · 스택 1개 일치 · 경력 신입/무관",
      "flags": []
    }
  ]
}